timer/__init__.py
timer/timer.py
msaligs_timer-0.1.0.dist-info/METADATA
msaligs_timer-0.1.0.dist-info/WHEEL
msaligs_timer-0.1.0.dist-info/top_level.txt
msaligs_timer-0.1.0.dist-info/RECORD
