Metadata-Version: 2.1
Name: msaligs-timer
Version: 0.1.0
Summary: A library for keeping track of running time of a function.
Author: msaligs
Author-email: msaligs@gmail.com
Classifier: Programming Language :: Python :: 3
Classifier: License :: OSI Approved :: MIT License
Classifier: Operating System :: OS Independent
Requires-Python: >=3.6
